svtyper/__init__.py
svtyper/classic.py
svtyper/parsers.py
svtyper/singlesample.py
svtyper/statistics.py
svtyper/utils.py
svtyper/version.py
svtyper-0.7.1.data/scripts/lib_stats.R
svtyper-0.7.1.data/scripts/sv_classifier.py
svtyper-0.7.1.data/scripts/update_info.py
svtyper-0.7.1.data/scripts/vcf_allele_freq.py
svtyper-0.7.1.data/scripts/vcf_group_multiline.py
svtyper-0.7.1.data/scripts/vcf_modify_header.py
svtyper-0.7.1.data/scripts/vcf_paste.py
svtyper-0.7.1.dist-info/LICENSE
svtyper-0.7.1.dist-info/METADATA
svtyper-0.7.1.dist-info/WHEEL
svtyper-0.7.1.dist-info/entry_points.txt
svtyper-0.7.1.dist-info/top_level.txt
svtyper-0.7.1.dist-info/RECORD
