Metadata-Version: 2.1
Name: svtyper
Version: 0.7.1
Summary: Bayesian genotyper for structural variants
Home-page: https://github.com/hall-lab/svtyper
Author: Colby Chiang (colbychiang@wustl.edu)
Author-email: colbychiang@wustl.edu
License: MIT License
Platform: UNKNOWN
Classifier: Intended Audience :: Science/Research
Classifier: Topic :: Scientific/Engineering :: Bio-Informatics
Classifier: License :: OSI Approved :: MIT License
Classifier: Programming Language :: Python :: 2.7
Requires-Dist: pysam (>=0.15.0)
Requires-Dist: numpy
Requires-Dist: scipy
Requires-Dist: cytoolz (>=0.8.2)
